amzn-aws-glue-ml-libs-python/__init__.py
amzn_aws_glue_ml_libs_python/__init__.py
amzn_aws_glue_ml_libs_python-6.1.5.dist-info/METADATA
amzn_aws_glue_ml_libs_python-6.1.5.dist-info/WHEEL
amzn_aws_glue_ml_libs_python-6.1.5.dist-info/top_level.txt
amzn_aws_glue_ml_libs_python-6.1.5.dist-info/RECORD
