Metadata-Version: 2.1
Name: amzn-aws-glue-ml-libs-python
Version: 6.1.5
Summary: A simple Python package
Home-page: https://github.com/yourusername/my_package
Author: Your Name
Author-email: your.email@example.com
Classifier: Programming Language :: Python :: 3
Classifier: License :: OSI Approved :: MIT License
Classifier: Operating System :: OS Independent
Requires-Python: >=3.6
Requires-Dist: requests
